GSMTC35/GSMTC35.py
GSMTC35/__init__.py
GSMTC35-2.1.1.dist-info/LICENSE.md
GSMTC35-2.1.1.dist-info/METADATA
GSMTC35-2.1.1.dist-info/WHEEL
GSMTC35-2.1.1.dist-info/top_level.txt
GSMTC35-2.1.1.dist-info/RECORD
