Metadata-Version: 2.1
Name: GSMTC35
Version: 2.1.1
Summary: GSM TC35/MC35 controller (Send/Receive SMS/MMS/Call and a lot more!)
Home-page: https://github.com/QuentinCG/GSM-TC35-Python-Library
Author: Quentin Comte-Gaz
Author-email: quentin@comte-gaz.com
License: MIT
Keywords: gsm pdu tc35 mc35 at sms mms call phone pin puk phonebook imei imsi ucs2 7bit forward unlock lock
Platform: any
Classifier: Development Status :: 5 - Production/Stable
Classifier: Topic :: Communications :: Telephony
Classifier: Topic :: Terminals :: Serial
Classifier: Topic :: Software Development :: Libraries
Classifier: Topic :: Software Development :: Libraries :: Python Modules
Classifier: Intended Audience :: Developers
Classifier: License :: OSI Approved :: MIT License
Classifier: Operating System :: Microsoft :: Windows
Classifier: Operating System :: POSIX :: Linux
Classifier: Operating System :: MacOS
Classifier: Natural Language :: English
Classifier: Programming Language :: Python :: 3
Classifier: Programming Language :: Python :: 3.2
Classifier: Programming Language :: Python :: 3.3
Classifier: Programming Language :: Python :: 3.4
Classifier: Programming Language :: Python :: 3.5
Classifier: Programming Language :: Python :: 3.6
Classifier: Programming Language :: Python :: 3.7
Classifier: Programming Language :: Python :: 3.8
License-File: LICENSE.md
Requires-Dist: pyserial
Provides-Extra: restapi
Requires-Dist: flask ; extra == 'restapi'
Requires-Dist: flask-restful ; extra == 'restapi'
Requires-Dist: flask-httpauth ; extra == 'restapi'
Requires-Dist: pyopenssl ; extra == 'restapi'
